syft_core/__init__.py
syft_core/client_shim.py
syft_core/config.py
syft_core/constants.py
syft_core/exceptions.py
syft_core/permissions.py
syft_core/py.typed
syft_core/types.py
syft_core/url.py
syft_core/workspace.py
syft_core-0.3.0.dist-info/METADATA
syft_core-0.3.0.dist-info/WHEEL
syft_core-0.3.0.dist-info/RECORD
